{
  "description": "301 редиректы со старого сайта velaslav.rus → 2980738.ru. SEO-команда может править без деплоя.",
  "lastUpdated": "2026-06-21",
  "redirects": [
    {
      "source": "/onlayn-shkola-potrebitelskoy-kooperatsii",
      "destination": "/",
      "permanent": true
    },
    {
      "source": "/obuchenie-na-onlayn-kursah-potrebitelskoy-kooperatsii",
      "destination": "/kursy-obuchenie-potrebitelskoy-kooperatsii-onlayn",
      "permanent": true
    },
    {
      "source": "/kursy",
      "destination": "/kursy-obuchenie-potrebitelskoy-kooperatsii-onlayn",
      "permanent": true
    },
    {
      "source": "/potrebitelskiy-kooperativ-vse-vygody",
      "destination": "/",
      "permanent": true
    },
    {
      "source": "/kak-otkryt-kooperativ-potrebitelskiy-obschestvo-sdelat-poshagovaya-instruktsiya",
      "destination": "/kursy-obuchenie-potrebitelskoy-kooperatsii-onlayn",
      "permanent": true
    },
    {
      "source": "/uslugi",
      "destination": "/uslugi-dlya-potrebitelskih-kooperativov",
      "permanent": true
    },
    {
      "source": "/pomosch-proektu",
      "destination": "/",
      "permanent": true
    },
    {
      "source": "/paket-bazovyy",
      "destination": "/kursy-obuchenie-potrebitelskoy-kooperatsii-onlayn",
      "permanent": true
    },
    {
      "source": "/paket-bazovyy-kursy-obucheniya-potrebkooperatsii-onlayn",
      "destination": "/kursy-obuchenie-potrebitelskoy-kooperatsii-onlayn",
      "permanent": true
    },
    {
      "source": "/paket-optimalnyy",
      "destination": "/kursy-obuchenie-potrebitelskoy-kooperatsii-onlayn",
      "permanent": true
    },
    {
      "source": "/paket-vip",
      "destination": "/kursy-obuchenie-potrebitelskoy-kooperatsii-onlayn",
      "permanent": true
    },
    {
      "source": "/spetspredlozhenie-start",
      "destination": "/kursy-obuchenie-potrebitelskoy-kooperatsii-onlayn",
      "permanent": true
    },
    {
      "source": "/video-answers",
      "destination": "/faq",
      "permanent": true
    },
    {
      "source": "/video-answers/what-is-a-consumer-cooperative",
      "destination": "/faq",
      "permanent": true
    },
    {
      "source": "/test",
      "destination": "/",
      "permanent": true
    },
    {
      "source": "/test-donat",
      "destination": "/",
      "permanent": true
    },
    {
      "source": "/2323",
      "destination": "/",
      "permanent": true
    },
    {
      "source": "/blog/yuridicheskaya-baza",
      "destination": "/blog",
      "permanent": true
    },
    {
      "source": "/blog/nalogi-i-uchet",
      "destination": "/blog",
      "permanent": true
    },
    {
      "source": "/blog/kejsy-istorii-uspekha",
      "destination": "/blog",
      "permanent": true
    },
    {
      "source": "/blog/dokumenty-shablony",
      "destination": "/blog",
      "permanent": true
    },
    {
      "source": "/blog/poleznaya-informatsiya",
      "destination": "/blog",
      "permanent": true
    },
    {
      "source": "/about",
      "destination": "/about-us",
      "permanent": true
    },
    {
      "source": "/uslugi/audit-ustava",
      "destination": "/uslugi/audit-ustava-pk",
      "permanent": true
    },
    {
      "source": "/konsultacii",
      "destination": "/potrebitelskiy-kooperativ-konsultatsii",
      "permanent": true
    }
  ]
}